pyconfs/__init__.py
pyconfs/_converters.py
pyconfs/_exceptions.py
pyconfs/_types.py
pyconfs/_util.py
pyconfs/configuration.py
pyconfs/formats/__init__.py
pyconfs/formats/formats.json
pyconfs/readers/__init__.py
pyconfs/readers/ini.py
pyconfs/readers/json.py
pyconfs/readers/toml.py
pyconfs/readers/yaml.py
pyconfs/writers/__init__.py
pyconfs/writers/ini.py
pyconfs/writers/json.py
pyconfs/writers/toml.py
pyconfs/writers/yaml.py
pyconfs-0.5.5.dist-info/LICENSE
pyconfs-0.5.5.dist-info/WHEEL
pyconfs-0.5.5.dist-info/METADATA
pyconfs-0.5.5.dist-info/RECORD
