Metadata-Version: 2.1
Name: pyconfs
Version: 0.5.5
Summary: PyConfs, unified handling of configuration files for Python
Home-page: https://github.com/gahjelle/pyconfs
Keywords: configuration ini json toml yml
Author: Geir Arne Hjelle
Author-email: geirarne@gmail.com
Requires-Python: >=3.6
Classifier: Development Status :: 4 - Beta
Classifier: Intended Audience :: Developers
Classifier: License :: OSI Approved :: MIT License
Classifier: Natural Language :: English
Classifier: Operating System :: MacOS
Classifier: Operating System :: Microsoft
Classifier: Operating System :: POSIX :: Linux
Classifier: Programming Language :: Python :: 3.6
Classifier: Programming Language :: Python :: 3.7
Classifier: Programming Language :: Python :: 3.8
Classifier: Programming Language :: Python :: 3.9
Classifier: Programming Language :: Python :: 3.10
Classifier: Topic :: Software Development :: Libraries :: Python Modules
Requires-Dist: importlib_resources; python_version < '3.7'
Requires-Dist: pyplugs
Requires-Dist: black ; extra == "dev"
Requires-Dist: bumpversion ; extra == "dev"
Requires-Dist: flake8 ; extra == "dev"
Requires-Dist: flit ; extra == "dev"
Requires-Dist: interrogate ; extra == "dev"
Requires-Dist: isort ; extra == "dev"
Requires-Dist: mypy ; extra == "dev"
Requires-Dist: pre-commit ; extra == "dev"
Requires-Dist: mkdocs ; extra == "doc"
Requires-Dist: black ; extra == "test"
Requires-Dist: flake8 ; extra == "test"
Requires-Dist: interrogate ; extra == "test"
Requires-Dist: isort ; extra == "test"
Requires-Dist: mypy ; extra == "test"
Requires-Dist: pytest ; extra == "test"
Requires-Dist: pytest-cov ; extra == "test"
Requires-Dist: tox ; extra == "test"
Requires-Dist: toml ; extra == "toml"
Requires-Dist: PyYAML ; extra == "yaml"
Provides-Extra: dev
Provides-Extra: doc
Provides-Extra: test
Provides-Extra: toml
Provides-Extra: yaml
